Workbook

Sheet Anleitung
B2: ARKTIK Klimasysteme — Margenkalkulation
B3: Erstellt am 31.08.2026. Alle Zahlen sind Annahmen und müssen durch echte Angebote ersetzt werden.
B5: So benutzen Sie diese Mappe
B6: Alles, was BLAU geschrieben ist, dürfen und sollen Sie ändern. Schwarze Zellen sind Formeln —
B7: wenn Sie die überschreiben, rechnet die Mappe falsch.
B8: GELB hinterlegte Zellen sind Annahmen, die Sie zuerst prüfen sollten. Vor allem der Wechselkurs.
B10: Die vier Blätter
B11: Annahmen Alles, was für alle Geräte gleich gilt: Wechselkurs, Fracht, Zoll, Gebühren, Retouren.
B12: Kalkulation Einkaufspreis, Landepreis und Deckungsbeitrag je Gerät. Das Kernstück.
B13: Container Was eine Erstbestellung kostet und ab welcher Verkaufsquote sie sich lohnt.
B14: Marktpreise Was Wettbewerber in Deutschland verlangen. Recherchiert, mit Quelle.
B16: Die drei Begriffe, um die es geht
... B38: Sobald das erste Angebot aus China vorliegt, tragen Sie den echten FOB-Preis ein.

Sheet Annahmen
B2: Annahmen
B3: Blau = ändern Sie hier. Gelb = zuerst prüfen.
B5: Einkauf und Import | C5: Wert | D5: Erläuterung
B6: Wechselkurs (EUR je USD) | C6: 0.92 | D6: BITTE PRÜFEN — Tageskurs eintragen. Ändert alle Einkaufspreise.
B7: Seefracht je 40-Fuß-Container (EUR) | C7: 3200 | D7: China–Nordeuropa. Schwankt stark, 2.500 bis 4.500 € sind üblich.
B8: Zollsatz auf Klimageräte | C8: 0.022 | D8: Position 8415. Berechnungsgrundlage ist Warenwert plus Fracht.
B9: Entsorgungs- und Verpackungsgebühren je Gerät (EUR) | C9: 3 | D9: WEEE-Beteiligung, duales System, Batteriegesetz.
B10: Einmalkosten je Modell (EUR) | C10: 6000 | D10: Prüfberichte, EPREL, Übersetzung der Anleitung, Fabrikaudit, Muster.
B12: Verkauf | C12: Wert | D12: Erläuterung
B13: Mehrwertsteuer | C13: 0.19 | D13: Regelbesteuerung.
B14: Zahlungsgebühr (vom Bruttoumsatz) | C14: 0.02 | D14: Karte über Stripe ca. 1,5 %, PayPal und Klarna deutlich mehr. Mischsatz.
B15: Versandkosten je Sendung, die Sie tragen (EUR) | C15: 32 | D15: Spedition innerhalb Deutschlands. Fällt an, wenn Sie versandkostenfrei liefern.
B16: Schwelle für versandkostenfreie Lieferung (EUR) | C16: 499 | D16: Steht so auf der Website und in stripe/catalog.json.
B18: Risiken | C18: Wert | D18: Erläuterung
B19: Retourenquote | C19: 0.05 | D19: Fernabsatz mit 14 Tagen Widerruf. 3 bis 6 % sind bei Weißware normal.
B20: Wertverlust je Retoure (vom Landepreis) | C20: 0.4 | D20: Ein zurückgesendetes Gerät ist oft nur noch als B-Ware verkäuflich.
B21: Rückstellung Gewährleistung (vom Nettoumsatz) | C21: 0.025 | D21: Zwei Jahre Gewährleistung. Fälle kommen meist im zweiten Sommer.
B23: Hinweis
B24: Die Einfuhrumsatzsteuer taucht hier bewusst nicht auf: Sie zahlen sie beim Import, holen sie aber als Vorsteuer zurück. Sie ist kein Kostenfaktor, sondern nur Liquidität — und steht deshalb auf dem Blatt „Container“.

Sheet Kalkulation
B2: Kalkulation je Gerät
B3: Links die Geräte ohne Montage, rechts die zur Selbstmontage mit Außengerät. Blaue Zellen ändern.
B5: Ohne Montage · Selbstmontage | C5: Zweikanal 9.000 BTU | D5: Zweikanal 12.000 BTU | E5: Quick-Connect 9.000 BTU | F5: Quick-Connect 12.000 BTU | G5: Erläuterung
B7: EINKAUF
B8: Einkaufspreis FOB je Gerät (USD) | C8: 150 | D8: 180 | E8: 175 | F8: 200 | G8: Angebot der Fabrik, geliefert bis Hafen China. Hier den echten Wert eintragen.
B9: Stück je 40-Fuß-Container | C9: 320 | D9: 260 | E9: 200 | F9: 170 | G9: Fragen Sie den Lieferanten. Split-Sets brauchen mehr Platz als Mobilgeräte.
B10: Einkaufspreis FOB je Gerät (EUR) | C10: =C8*Annahmen!$C$6 | D10: =D8*Annahmen!$C$6 | E10: =E8*Annahmen!$C$6 | F10: =F8*Annahmen!$C$6 | G10: FOB in Euro, zum Kurs aus dem Blatt Annahmen.
B11: Seefracht je Gerät | C11: =Annahmen!$C$7/C9 | D11: =Annahmen!$C$7/D9 | E11: =Annahmen!$C$7/E9 | F11: =Annahmen!$C$7/F9 | G11: Containerfracht geteilt durch die Stückzahl.
B12: Zoll je Gerät | C12: =(C10+C11)*Annahmen!$C$8 | D12: =(D10+D11)*Annahmen!$C$8 | E12: =(E10+E11)*Annahmen!$C$8 | F12: =(F10+F11)*Annahmen!$C$8 | G12: Auf Warenwert plus Fracht.
B13: Entsorgung und Verpackung je Gerät | C13: =Annahmen!$C$9 | D13: =Annahmen!$C$9 | E13: =Annahmen!$C$9 | F13: =Annahmen!$C$9 | G13: WEEE, duales System, Batteriegesetz.
B14: Einmalkosten je Gerät | C14: =Annahmen!$C$10/C9 | D14: =Annahmen!$C$10/D9 | E14: =Annahmen!$C$10/E9 | F14: =Annahmen!$C$10/F9 | G14: Zertifizierung und Muster, verteilt auf die erste Containerladung.
B15: Landepreis je Gerät | C15: =SUM(C10:C14) | D15: =SUM(D10:D14) | E15: =SUM(E10:E14) | F15: =SUM(F10:F14) | G15: Ihr echter Einkaufspreis, wenn das Gerät im Lager steht.
B17: VERKAUF
B18: Ihr Verkaufspreis (brutto) | C18: 549 | D18: 649 | E18: 649 | F18: 749 | G18: Preis auf der Website, inklusive Mehrwertsteuer.
B19: Vergleichspreis Wettbewerb (brutto) | C19: 449 | D19: 549 | E19: 477 | F19: 570 | G19: Recherchierte Marktpreise, siehe Blatt Marktpreise.
B20: Abstand zum Wettbewerb | C20: =IF(C19=0,0,C18/C19-1) | D20: =IF(D19=0,0,D18/D19-1) | E20: =IF(E19=0,0,E18/E19-1) | F20: =IF(F19=0,0,F18/F19-1) | G20: Positiv heißt: Sie sind teurer. Das muss ein Argument rechtfertigen.
B21: Nettoumsatz je Gerät | C21: =C18/(1+Annahmen!$C$13) | D21: =D18/(1+Annahmen!$C$13) | E21: =E18/(1+Annahmen!$C$13) | F21: =F18/(1+Annahmen!$C$13) | G21: Was nach Abzug der Mehrwertsteuer bei Ihnen ankommt.
B23: WAS VOM VERKAUFSPREIS ABGEHT
B24: Landepreis (Wareneinsatz) | C24: =C15 | D24: =D15 | E24: =E15 | F24: =F15 | G24: Aus dem Abschnitt Einkauf.
B25: Zahlungsgebühr | C25: =C18*Annahmen!$C$14 | D25: =D18*Annahmen!$C$14 | E25: =E18*Annahmen!$C$14 | F25: =F18*Annahmen!$C$14 | G25: Stripe, PayPal, Klarna. Wird auf den Bruttobetrag berechnet.
B26: Versandkosten, die Sie tragen | C26: =IF(C18>=Annahmen!$C$16,Annahmen!$C$15,0) | D26: =IF(D18>=Annahmen!$C$16,Annahmen!$C$15,0) | E26: =IF(E18>=Annahmen!$C$16,Annahmen!$C$15,0) | F26: =IF(F18>=Annahmen!$C$16,Annahmen!$C$15,0) | G26: Ab der Freigrenze zahlen Sie den Versand. Das ist echtes Geld.
B27: Retourenrisiko | C27: =Annahmen!$C$19*(C15*Annahmen!$C$20+Annahmen!$C$15*2) | D27: =Annahmen!$C$19*(D15*Annahmen!$C$20+Annahmen!$C$15*2) | E27: =Annahmen!$C$19*(E15*Annahmen!$C$20+Annahmen!$C$15*2) | F27: =Annahmen!$C$19*(F15*Annahmen!$C$20+Annahmen!$C$15*2) | G27: Quote × (Wertverlust am Gerät + Hin- und Rückversand).
B28: Rückstellung Gewährleistung | C28: =C21*Annahmen!$C$21 | D28: =D21*Annahmen!$C$21 | E28: =E21*Annahmen!$C$21 | F28: =F21*Annahmen!$C$21 | G28: Für Reparaturen und Austauschgeräte im zweiten Jahr.
B30: Deckungsbeitrag je Gerät | C30: =C21-C24-C25-C26-C27-C28 | D30: =D21-D24-D25-D26-D27-D28 | E30: =E21-E24-E25-E26-E27-E28 | F30: =F21-F24-F25-F26-F27-F28 | G30: Was übrig bleibt. Davon zahlen Sie Lager, Werbung, Versicherung und sich selbst.
B31: Marge (vom Nettoumsatz) | C31: =IF(C21=0,0,C30/C21) | D31: =IF(D21=0,0,D30/D21) | E31: =IF(E21=0,0,E30/E21) | F31: =IF(F21=0,0,F30/F21) | G31: Unter 30 % wird es im Onlinehandel eng, über 45 % ist gut.
B32: Aufschlagsfaktor auf den Landepreis | C32: =IF(C15=0,0,C18/C15) | D32: =IF(D15=0,0,D18/D15) | E32: =IF(E15=0,0,E18/E15) | F32: =IF(F15=0,0,F18/F15) | G32: Im Elektrohandel sind 2,5× bis 3,5× auf den Landepreis üblich.
B33: Niedrigster Verkaufspreis ohne Verlust (brutto) | C33: =(C24+C26+C27)*(1+Annahmen!$C$13)/((1-Annahmen!$C$21)-Annahmen!$C$14*(1+Annahmen!$C$13)) | D33: =(D24+D26+D27)*(1+Annahmen!$C$13)/((1-Annahmen!$C$21)-Annahmen!$C$14*(1+Annahmen!$C$13)) | E33: =(E24+E26+E27)*(1+Annahmen!$C$13)/((1-Annahmen!$C$21)-Annahmen!$C$14*(1+Annahmen!$C$13)) | F33: =(F24+F26+F27)*(1+Annahmen!$C$13)/((1-Annahmen!$C$21)-Annahmen!$C$14*(1+Annahmen!$C$13)) | G33: Darunter legen Sie bei jedem Gerät drauf. Versandkosten wie beim aktuellen Preis angesetzt.
B35: Lesehilfe
B36: Der Aufschlagsfaktor ist die Zahl, die Händler im Kopf haben. Verkaufspreis geteilt durch Landepreis. Unter 2,5 verdienen Sie im Onlinehandel nach Werbung und Retouren meist nichts mehr, weil Zahlungsgebühr, Versand und Rückstellungen den Rest fressen.

Sheet Container
B2: Was eine Erstbestellung kostet
B3: Beispiel für ein Modell. Wählen Sie über die blaue Zelle, welches.
B5: Bestellung | C5: Wert | D5: Erläuterung
B6: Welches Modell? (1 bis 4) | C6: 2 | D6: 1 = Zweikanal 9k · 2 = Zweikanal 12k · 3 = Quick-Connect 9k · 4 = Quick-Connect 12k
B7: Stück je Container | C7: =INDEX(Kalkulation!$C$9:$F$9,1,$C$6) | D7: Aus der Kalkulation.
B8: Landepreis je Gerät | C8: =INDEX(Kalkulation!$C$15:$F$15,1,$C$6) | D8: Aus der Kalkulation.
B9: Verkaufspreis brutto | C9: =INDEX(Kalkulation!$C$18:$F$18,1,$C$6) | D9: Aus der Kalkulation.
B10: Deckungsbeitrag je Gerät | C10: =INDEX(Kalkulation!$C$30:$F$30,1,$C$6) | D10: Aus der Kalkulation.
B12: Kapitalbedarf | C12: Wert | D12: Erläuterung
B13: Wareneinsatz (FOB gesamt) | C13: =INDEX(Kalkulation!$C$10:$F$10,1,$C$6)*C7 | D13: Das zahlen Sie der Fabrik, meist 30 % im Voraus.
B14: Seefracht | C14: =Annahmen!C7 | D14: Ein Container.
B15: Zoll | C15: =(C13+C14)*Annahmen!C8 | D15: Auf Warenwert plus Fracht.
B16: Einmalkosten Zertifizierung | C16: =Annahmen!C10 | D16: Fällt nur beim ersten Container je Modell an.
B17: Entsorgungs- und Verpackungsgebühren | C17: =Annahmen!C9*C7 | D17: Für die ganze Menge.
B18: Gebundenes Kapital | C18: =SUM(C13:C17) | D18: So viel Geld liegt im Lager, bevor Sie den ersten Euro einnehmen.
B19: Einfuhrumsatzsteuer (nur Liquidität) | C19: =(C13+C14+C15)*Annahmen!C13 | D19: Zahlen Sie beim Import, holen Sie als Vorsteuer zurück. Kein Kostenfaktor, aber Sie brauchen das Geld zwischenzeitlich.
B21: Ergebnis, wenn alles verkauft wird | C21: Wert | D21: Erläuterung
B22: Umsatz brutto | C22: =C9*C7 | D22: Bei 100 % Verkaufsquote.
B23: Deckungsbeitrag gesamt | C23: =C10*C7 | D23: Vor Lager, Werbung, Versicherung und Steuern.
B25: Ab wann lohnt es sich | C25: Wert | D25: Erläuterung
B26: Geldrückfluss je verkauftem Gerät | C26: =C10+C8 | D26: Deckungsbeitrag plus Wareneinsatz — der Wareneinsatz steckt schon im gebundenen Kapital und darf hier nicht doppelt abgezogen werden.
B27: Stückzahl für Kostendeckung | C27: =IF(C26=0,0,C18/C26) | D27: So viele Geräte müssen verkauft sein, bis das eingesetzte Geld wieder da ist.
B28: Das entspricht einer Verkaufsquote von | C28: =IF(C7=0,0,C27/C7) | D28: Bezogen auf die Containermenge.
B29: Ergebnis bei 70 % Verkaufsquote | C29: =C10*C7*0.7-Annahmen!C10*0.3 | D29: Deckungsbeitrag aus 70 % der Menge. Die Einmalkosten für die unverkauften 30 % sind noch nicht wieder eingespielt und daher abgezogen. Der Wareneinsatz der Restmenge bleibt als Lagerwert erhalten.
B31: Was diese Rechnung nicht enthält
B32: Lagermiete, Werbung, Ihre Arbeitszeit, Versicherung, Steuerberatung, Einkommensteuer. Und den Fall, dass der Sommer 2027 kühl wird und die Hälfte des Containers ein Jahr länger steht. Rechnen Sie mit der 70-Prozent-Zeile, nicht mit der 100-Prozent-Zeile.

Sheet Marktpreise
B2: Was der Markt verlangt
B3: Recherchiert am 31.08.2026. Preise ändern sich — vor der Preisfestsetzung nachprüfen.
B5: Produkt | C5: Preis | D5: Anbieter | E5: Quelle / Anmerkung
B6: GERÄTE OHNE MONTAGE
B7: Mobiles Klimagerät 12.000 BTU, bis 48 m² | C7: 449 | D7: MediaMarkt | E7: Einschlauchgerät, Standardware im Elektrohandel
B8: Testsieger-Klasse Stiftung Warentest | C8: 400 | D8: Handel allgemein | E8: Spanne der gut bewerteten Geräte: rund 300 bis 500 €
B9: De'Longhi Pinguino PAC EX Serie | C9: 600 | D9: Fachhandel | E9: Zweischlauch-Premium, je nach Modell 500 bis 800 €
B11: SELBSTMONTAGE MIT AUSSENGERÄT
B12: Heiko 12.000 BTU R32 Split | C12: 477 | D12: eBay | E12: inklusive Versand
B13: BeCool BC12SK2101QW Quick Connect | C13: 570 | D13: eBay | E13: zuzüglich 23,99 € Versand, A++, R32 vorgefüllt
B14: DANYON XA35QC Quick Connect 12.000 BTU | C14: k. A. | D14: danyon.de | E14: mit 5-m-Montageset; Anbieter positioniert es für den Fachbetrieb
B15: Weitere Anbieter im deutschen Markt | C15: k. A. | D15: Kältebringer, KlimaWorld, environ | E15: Die Nische ist bereits besetzt — siehe Anmerkung unten
B17: Die wichtigste Erkenntnis aus dieser Recherche
B18: Die beiden Produktlinien stehen in völlig unterschiedlichen Märkten. Selbstmontage mit Außengerät: Hier gibt es in Deutschland bereits DANYON, BeCool, Kältebringer, KlimaWorld und environ, mit Preisen zwischen 477 und 570 € für 12.000 BTU. Der Preis auf Ihrer Website liegt darüber. In diesen Markt kommen Sie nur über den Preis hinein — und Preiskampf gegen eingeführte Anbieter ist als Neueinsteiger die schlechteste aller Ausgangslagen. Geräte ohne Montage: Der Markt ist groß, aber fast vollständig mit Einschlauchgeräten besetzt (MediaMarkt 449 € für 12.000 BTU). Zweischlauchgeräte gibt es fast nur von De'Longhi im Premiumbereich. Dazwischen ist Platz — und Sie haben ein technisches Argument, das stimmt und das der Kunde versteht. Empfehlung: Starten Sie mit einer Linie, nicht mit zweien. Die ohne Montage.
